data_info/__init__.py
data_info/info.py
preprocessing/__init__.py
preprocessing/categorical.py
preprocessing/exception.py
preprocessing/filtering.py
preprocessing/groupby.py
preprocessing/missing_value.py
preprocessing/outlier.py
preprocessing/preproc_manager.py
preprocessing/preproc_utils.py
preprocessing/replace_value.py
preprocessing/scaler.py
preprocessing/test/__init__.py
preprocessing/test/history_example.py
neuralworks_preproc-0.0.37.dist-info/METADATA
neuralworks_preproc-0.0.37.dist-info/WHEEL
neuralworks_preproc-0.0.37.dist-info/top_level.txt
neuralworks_preproc-0.0.37.dist-info/RECORD
