Metadata-Version: 2.1
Name: neuralworks-preproc
Version: 0.0.37
Summary: 2023/02/17
Home-page: https://neuralworks.io
Download-URL: https://github.com/Neuralworks-io/
